README.txt
setup.cfg
setup.py
Products/__init__.py
Products.ATTalesExpressionCriterion.egg-info/PKG-INFO
Products.ATTalesExpressionCriterion.egg-info/SOURCES.txt
Products.ATTalesExpressionCriterion.egg-info/dependency_links.txt
Products.ATTalesExpressionCriterion.egg-info/entry_points.txt
Products.ATTalesExpressionCriterion.egg-info/namespace_packages.txt
Products.ATTalesExpressionCriterion.egg-info/not-zip-safe
Products.ATTalesExpressionCriterion.egg-info/requires.txt
Products.ATTalesExpressionCriterion.egg-info/top_level.txt
Products/ATTalesExpressionCriterion/README.txt
Products/ATTalesExpressionCriterion/__init__.py
Products/ATTalesExpressionCriterion/config.py
Products/ATTalesExpressionCriterion/configure.zcml
Products/ATTalesExpressionCriterion/criteria/__init__.py
Products/ATTalesExpressionCriterion/criteria/talesexpression.py
Products/ATTalesExpressionCriterion/profiles/default/metadata.xml
Products/ATTalesExpressionCriterion/profiles/default/types.xml
Products/ATTalesExpressionCriterion/profiles/default/types/ATTalesExpressionCriterion.xml
docs/HISTORY.txt
docs/INSTALL.txt
docs/LICENSE.txt