Metadata-Version: 1.0
Name: Products.ATTalesExpressionCriterion
Version: 1.0dev-r69725
Summary: Smart folder criterion that stores TALES Expressions.
Home-page: http://svn.plone.org/svn/collective/Products.ATTalesExpressionCriterion
Author: Andreas Gabriel
Author-email: gabriel@hrz.uni-marbug.de
License: ZPL
Keywords: ATContentTypes Collection Topic Criterion
Platform: UNKNOWN
Classifier: Framework :: Plone
Classifier: Framework :: Zope2
Classifier: Programming Language :: Python
